jpf/__init__.py
jpf-0.3.0.dist-info/entry_points.txt
jpf-0.3.0.dist-info/LICENSE
jpf-0.3.0.dist-info/WHEEL
jpf-0.3.0.dist-info/METADATA
jpf-0.3.0.dist-info/RECORD
