Metadata-Version: 2.1
Name: jpf
Version: 0.3.0
Summary: Pretty format all your json files at once in place with three characters
Home-page: https://github.com/fxwiegand/jpf
License: MIT
Author: fxwiegand
Author-email: fxwiegand@wgdnet.de
Requires-Python: >=3.7
Classifier: License :: OSI Approved :: MIT License
Classifier: Programming Language :: Python :: 3
Classifier: Programming Language :: Python :: 3.10
Classifier: Programming Language :: Python :: 3.7
Classifier: Programming Language :: Python :: 3.8
Classifier: Programming Language :: Python :: 3.9
Requires-Dist: plac (>=1.3.5,<2.0.0)
Project-URL: Repository, https://github.com/fxwiegand/jpf
